Workbook
Name Slicer_expense_category: #N/A
Name Slicer_expense_category1: #N/A
Name Slicer_expense_type: #N/A
Name Slicer_funding_source: #N/A
Name Slicer_ministry_name: #N/A

Sheet dashboard

Sheet rough_work ref_to_dashboard
G1: Row Labels | H1: Sum of budget_amount | I1: Sum of amount_spent | J1: utilization%
A2: total approved budget | B2: ="$"&ROUND(GETPIVOTDATA("[Measures].[Sum of budget_amount]",pivot_table!$A$1)/100000000, 1)&"B" -> $658.7B | G2: =pivot_table!A3 -> Ministry of Artificial Intelligence | H2: =pivot_table!B3 -> 2.40984e+09 | I2: =pivot_table!C3 -> 1.0883318e+09 | J2: =I2/H2 -> 0.45161996
A3: total actual expenditure | B3: ="$"&ROUND(GETPIVOTDATA("[Measures].[Sum of amount_spent]",pivot_table!$A$1)/100000000, 1)&"B" -> $167.2B | G3: =pivot_table!A2 -> Ministry of Agriculture | H3: =pivot_table!B2 -> 8.71773e+08 | I3: =pivot_table!C2 -> 3.4345925e+08 | J3: =I3/H3 -> 0.39397785
A4: budget utilization | B4: =GETPIVOTDATA("[Measures].[Sum of amount_spent]",pivot_table!$A$1)/GETPIVOTDATA("[Measures].[Sum of budget_amount]",pivot_table!$A$1) -> 0.25374752 | G4: =pivot_table!A5 -> Ministry of Energy and Natural Resources | H4: =pivot_table!B5 -> 5937825000 | I4: =pivot_table!C5 -> 1.7004774e+09 | J4: =I4/H4 -> 0.28638052
A5: capital expense utilization % | B5: =GETPIVOTDATA("[Measures].[Sum of amount_spent]",pivot_table!$E$1,"[dim_expense_category].[expense_category]","[dim_expense_category].[expense_category].&[Capital]")/GETPIVOTDATA("[Measures].[Sum of budget_amount]",pivot_table!$E$1,"[dim_expense_category].[expense_category]","[dim_expense_category].[expense_category].&[Capital]") -> 0.2060113 | G5: =pivot_table!A18 -> Grand Total | H5: =pivot_table!B18 -> 6.5872976e+10 | I5: =pivot_table!C18 -> 1.6715104e+10 | J5: =I5/H5 -> 0.25374752
A6: operational expense utilization % | B6: =GETPIVOTDATA("[Measures].[Sum of amount_spent]",pivot_table!$E$1,"[dim_expense_category].[expense_category]","[dim_expense_category].[expense_category].&[Operational]")/GETPIVOTDATA("[Measures].[Sum of budget_amount]",pivot_table!$E$1,"[dim_expense_category].[expense_category]","[dim_expense_category].[expense_category].&[Operational]") -> 0.32258296 | G6: =pivot_table!A15 -> Ministry of Public Works | H6: =pivot_table!B15 -> 8.51473e+09 | I6: =pivot_table!C15 -> 2.0397093e+09 | J6: =I6/H6 -> 0.23955068
A7: ministries below 50% utilization | B7: =COUNTIF(J2:J9, "<0.5") -> 8 | G7: =pivot_table!A9 -> Ministry of Immigration | H7: =pivot_table!B9 -> 4502940000 | I7: =pivot_table!C9 -> 6.4415426e+08 | J7: =I7/H7 -> 0.14305193
G8: =pivot_table!A7 -> Ministry of Health | H8: =pivot_table!B7 -> 7624024000 | I8: =pivot_table!C7 -> 9.1812937e+08 | J8: =I8/H8 -> 0.12042582
G9: =pivot_table!A13 -> Ministry of National Defence | H9: =pivot_table!B13 -> 2.082075e+10 | I9: =pivot_table!C13 -> 1.496652e+08 | J9: =I9/H9 -> 0.0071882713
A11: =pivot_table!A22 -> Row Labels | B11: =pivot_table!B22 -> Sum of budget_amount | C11: =pivot_table!C22 -> Sum of amount_spent | D11: =pivot_table!D22 -> difference
A12: =pivot_table!A23 -> Building Construction and Renovation | B12: =pivot_table!B23 -> 3.8861295e+09 | C12: =pivot_table!C23 -> 6.7843385e+08 | D12: =pivot_table!D23 -> 0.17457829
A13: =pivot_table!A25 -> Employee Benefits and Pensions | B13: =pivot_table!B25 -> 3.2826326e+09 | C13: =pivot_table!C25 -> 7.598869e+08 | D13: =pivot_table!D25 -> 0.23148704 | G13: =pivot_table!A1 -> Row Labels | H13: =pivot_table!B1 -> Sum of budget_amount | I13: =pivot_table!C1 -> Sum of amount_spent
A14: =pivot_table!A29 -> IT Systems Implementation (ERP, Cybersecurity Systems) | B14: =pivot_table!B29 -> 5.4137307e+09 | C14: =pivot_table!C29 -> 5.5940038e+08 | D14: =pivot_table!D29 -> 0.10332992 | G14: =pivot_table!A13 -> Ministry of National Defence | H14: =pivot_table!B13 -> 2.082075e+10 | I14: =pivot_table!C13 -> 1.496652e+08
A15: =pivot_table!A32 -> Major Technology Hardware Purchases | B15: =pivot_table!B32 -> 1.0006235e+10 | C15: =pivot_table!C32 -> 6.5949868e+08 | D15: =pivot_table!D32 -> 0.065908772
A16: =pivot_table!A33 -> Office Supplies and Consumables | B16: =pivot_table!B33 -> 3.081208e+09 | C16: =pivot_table!C33 -> 5.4455815e+08 | D16: =pivot_table!D33 -> 0.17673528
A17: =pivot_table!A35 -> Public Facility Expansion Projects | B17: =pivot_table!B35 -> 3.2390206e+09 | C17: =pivot_table!C35 -> 5.819273e+08 | D17: =pivot_table!D35 -> 0.1796615
A18: =pivot_table!A37 -> Research and Innovation Capital Projects | B18: =pivot_table!B37 -> 2.9573088e+09 | C18: =pivot_table!C37 -> 6.7397752e+08 | D18: =pivot_table!D37 -> 0.22790232
A19: =pivot_table!A42 -> Vehicle Fleet Acquisition | B19: =pivot_table!B42 -> 4.8805297e+09 | C19: =pivot_table!C42 -> 1.1712364e+09 | D19: =pivot_table!D42 -> 0.23998141

Sheet pivot_table
A1: Row Labels | B1: Sum of budget_amount | C1: Sum of amount_spent | E1: Row Labels | F1: Sum of budget_amount | G1: Sum of amount_spent
A2: Ministry of Agriculture | B2: 8.71773e+08 | C2: 3.4345925e+08 | E2: Capital | F2: 3.889792e+10 | G2: 8.0134111e+09
A3: Ministry of Artificial Intelligence | B3: 2.40984e+09 | C3: 1.0883318e+09 | E3: Operational | F3: 2.6975056e+10 | G3: 8.7016933e+09
A4: Ministry of Emergency Management | B4: 2.3436092e+09 | C4: 1.6956946e+09 | E4: Grand Total | F4: 6.5872976e+10 | G4: 1.6715104e+10
A5: Ministry of Energy and Natural Resources | B5: 5937825000 | C5: 1.7004774e+09
A6: Ministry of Fisheries | B6: 754036500 | C6: 5.9261981e+08
A7: Ministry of Health | B7: 7624024000 | C7: 9.1812937e+08 | E7: Row Labels | F7: Sum of funding_amount
A8: Ministry of Housing and Infrastructure | B8: 426926400 | C8: 2.6545912e+08 | E8: federal_funding | F8: 3.6230137e+10
A9: Ministry of Immigration | B9: 4502940000 | C9: 6.4415426e+08 | E9: grant_funding | F9: 9.8809464e+09
A10: Ministry of Indigenous Services | B10: 5.40579e+08 | C10: 2.9778213e+08 | E10: internally_gen_funding | F10: 3.2936488e+09
A11: Ministry of International Trade | B11: 1554366800 | C11: 1.0179791e+09 | E11: provincial_funding | F11: 1.6468244e+10
A12: Ministry of Justice | B12: 3127334000 | C12: 2.0121406e+09 | E12: Grand Total | F12: 65872975910
A13: Ministry of National Defence | B13: 2.082075e+10 | C13: 1.496652e+08
A14: Ministry of Public Safety | B14: 2.569224e+09 | C14: 1.555735e+09
A15: Ministry of Public Works | B15: 8.51473e+09 | C15: 2.0397093e+09
A16: Ministry of Tourism | B16: 1.402954e+09 | C16: 1.1176661e+09
A17: Ministry of Transport | B17: 2.472064e+09 | C17: 1.2761014e+09
A18: Grand Total | B18: 6.5872976e+10 | C18: 1.6715104e+10
A22: Row Labels | B22: Sum of budget_amount | C22: Sum of amount_spent | D22: difference
A23: Building Construction and Renovation | B23: 3.8861295e+09 | C23: 6.7843385e+08 | D23: =GETPIVOTDATA("[Measures].[Sum of amount_spent]",$A$22,"[dim_expense_type].[expense_type]","[dim_expense_type].[expense_type].&[Building Construction and Renovation]")/GETPIVOTDATA("[Measures].[Sum of budget_amount]",$A$22,"[dim_expense_type].[expense_type]","[dim_expense_type].[expense_type].&[Building Construction and Renovation]") -> 0.17457829
A24: Data Center Development | B24: 1.8790511e+09 | C24: 8.8634362e+08 | D24: =GETPIVOTDATA("[Measures].[Sum of amount_spent]",$A$22,"[dim_expense_type].[expense_type]","[dim_expense_type].[expense_type].&[Data Center Development]")/GETPIVOTDATA("[Measures].[Sum of budget_amount]",$A$22,"[dim_expense_type].[expense_type]","[dim_expense_type].[expense_type].&[Data Center Development]") -> 0.47169745
A25: Employee Benefits and Pensions | B25: 3.2826326e+09 | C25: 7.598869e+08 | D25: =GETPIVOTDATA("[Measures].[Sum of amount_spent]",$A$22,"[dim_expense_type].[expense_type]","[dim_expense_type].[expense_type].&[Employee Benefits and Pensions]")/GETPIVOTDATA("[Measures].[Sum of budget_amount]",$A$22,"[dim_expense_type].[expense_type]","[dim_expense_type].[expense_type].&[Employee Benefits and Pensions]") -> 0.23148704
A26: Heavy Equipment Purchase | B26: 2.7447596e+09 | C26: 7.4395603e+08 | D26: =GETPIVOTDATA("[Measures].[Sum of amount_spent]",$A$22,"[dim_expense_type].[expense_type]","[dim_expense_type].[expense_type].&[Heavy Equipment Purchase]")/GETPIVOTDATA("[Measures].[Sum of budget_amount]",$A$22,"[dim_expense_type].[expense_type]","[dim_expense_type].[expense_type].&[Heavy Equipment Purchase]") -> 0.27104597
A27: Infrastructure Development Projects | B27: 2.51326e+09 | C27: 1.1757872e+09 | D27: =GETPIVOTDATA("[Measures].[Sum of amount_spent]",$A$22,"[dim_expense_type].[expense_type]","[dim_expense_type].[expense_type].&[Infrastructure Development Projects]")/GETPIVOTDATA("[Measures].[Sum of budget_amount]",$A$22,"[dim_expense_type].[expense_type]","[dim_expense_type].[expense_type].&[Infrastructure Development Projects]") -> 0.46783348
A28: IT Support and Software Subscriptions | B28: 1.2477864e+09 | C28: 7.9594581e+08 | D28: =GETPIVOTDATA("[Measures].[Sum of amount_spent]",$A$22,"[dim_expense_type].[expense_type]","[dim_expense_type].[expense_type].&[IT Support and Software Subscriptions]")/GETPIVOTDATA("[Measures].[Sum of budget_amount]",$A$22,"[dim_expense_type].[expense_type]","[dim_expense_type].[expense_type].&[IT Support and Software Subscriptions]") -> 0.63788629
A29: IT Systems Implementation (ERP, Cybersecurity Systems) | B29: 5.4137307e+09 | C29: 5.5940038e+08 | D29: =GETPIVOTDATA("[Measures].[Sum of amount_spent]",$A$22,"[dim_expense_type].[expense_type]","[dim_expense_type].[expense_type].&[IT Systems Implementation (ERP, Cybersecurity Systems)]")/GETPIVOTDATA("[Measures].[Sum of budget_amount]",$A$22,"[dim_expense_type].[expense_type]","[dim_expense_type].[expense_type].&[IT Systems Implementation (ERP, Cybersecurity Systems)]") -> 0.10332992
A30: Land Acquisition | B30: 1.3778947e+09 | C30: 8.8285016e+08 | D30: =GETPIVOTDATA("[Measures].[Sum of amount_spent]",$A$22,"[dim_expense_type].[expense_type]","[dim_expense_type].[expense_type].&[Land Acquisition]")/GETPIVOTDATA("[Measures].[Sum of budget_amount]",$A$22,"[dim_expense_type].[expense_type]","[dim_expense_type].[expense_type].&[Land Acquisition]") -> 0.64072397
A31: Maintenance and Repairs | B31: 3.5847583e+09 | C31: 9.942185e+08 | D31: =GETPIVOTDATA("[Measures].[Sum of amount_spent]",$A$22,"[dim_expense_type].[expense_type]","[dim_expense_type].[expense_type].&[Maintenance and Repairs]")/GETPIVOTDATA("[Measures].[Sum of budget_amount]",$A$22,"[dim_expense_type].[expense_type]","[dim_expense_type].[expense_type].&[Maintenance and Repairs]") -> 0.27734604
A32: Major Technology Hardware Purchases | B32: 1.0006235e+10 | C32: 6.5949868e+08 | D32: =GETPIVOTDATA("[Measures].[Sum of amount_spent]",$A$22,"[dim_expense_type].[expense_type]","[dim_expense_type].[expense_type].&[Major Technology Hardware Purchases]")/GETPIVOTDATA("[Measures].[Sum of budget_amount]",$A$22,"[dim_expense_type].[expense_type]","[dim_expense_type].[expense_type].&[Major Technology Hardware Purchases]") -> 0.065908772
A33: Office Supplies and Consumables | B33: 3.081208e+09 | C33: 5.4455815e+08 | D33: =GETPIVOTDATA("[Measures].[Sum of amount_spent]",$A$22,"[dim_expense_type].[expense_type]","[dim_expense_type].[expense_type].&[Office Supplies and Consumables]")/GETPIVOTDATA("[Measures].[Sum of budget_amount]",$A$22,"[dim_expense_type].[expense_type]","[dim_expense_type].[expense_type].&[Office Supplies and Consumables]") -> 0.17673528
A34: Professional and Consulting Fees | B34: 2.0573847e+09 | C34: 9.7438548e+08 | D34: =GETPIVOTDATA("[Measures].[Sum of amount_spent]",$A$22,"[dim_expense_type].[expense_type]","[dim_expense_type].[expense_type].&[Professional and Consulting Fees]")/GETPIVOTDATA("[Measures].[Sum of budget_amount]",$A$22,"[dim_expense_type].[expense_type]","[dim_expense_type].[expense_type].&[Professional and Consulting Fees]") -> 0.47360393
A35: Public Facility Expansion Projects | B35: 3.2390206e+09 | C35: 5.819273e+08 | D35: =GETPIVOTDATA("[Measures].[Sum of amount_spent]",$A$22,"[dim_expense_type].[expense_type]","[dim_expense_type].[expense_type].&[Public Facility Expansion Projects]")/GETPIVOTDATA("[Measures].[Sum of budget_amount]",$A$22,"[dim_expense_type].[expense_type]","[dim_expense_type].[expense_type].&[Public Facility Expansion Projects]") -> 0.1796615
A36: Public Outreach and Communication Costs | B36: 2.1790455e+09 | C36: 8.1009629e+08 | D36: =GETPIVOTDATA("[Measures].[Sum of amount_spent]",$A$22,"[dim_expense_type].[expense_type]","[dim_expense_type].[expense_type].&[Public Outreach and Communication Costs]")/GETPIVOTDATA("[Measures].[Sum of budget_amount]",$A$22,"[dim_expense_type].[expense_type]","[dim_expense_type].[expense_type].&[Public Outreach and Communication Costs]") -> 0.37176657
A37: Research and Innovation Capital Projects | B37: 2.9573088e+09 | C37: 6.7397752e+08 | D37: =GETPIVOTDATA("[Measures].[Sum of amount_spent]",$A$22,"[dim_expense_type].[expense_type]","[dim_expense_type].[expense_type].&[Research and Innovation Capital Projects]")/GETPIVOTDATA("[Measures].[Sum of budget_amount]",$A$22,"[dim_expense_type].[expense_type]","[dim_expense_type].[expense_type].&[Research and Innovation Capital Projects]") -> 0.22790232
A38: Salaries and Wages | B38: 3.2725857e+09 | C38: 8.7211301e+08 | D38: =GETPIVOTDATA("[Measures].[Sum of amount_spent]",$A$22,"[dim_expense_type].[expense_type]","[dim_expense_type].[expense_type].&[Salaries and Wages]")/GETPIVOTDATA("[Measures].[Sum of budget_amount]",$A$22,"[dim_expense_type].[expense_type]","[dim_expense_type].[expense_type].&[Salaries and Wages]") -> 0.2664905
A39: Training and Staff Development | B39: 3.046302e+09 | C39: 9.4413519e+08 | D39: =GETPIVOTDATA("[Measures].[Sum of amount_spent]",$A$22,"[dim_expense_type].[expense_type]","[dim_expense_type].[expense_type].&[Training and Staff Development]")/GETPIVOTDATA("[Measures].[Sum of budget_amount]",$A$22,"[dim_expense_type].[expense_type]","[dim_expense_type].[expense_type].&[Training and Staff Development]") -> 0.3099283
A40: Travel and Accommodation Expenses | B40: 1.8157521e+09 | C40: 9.6467569e+08 | D40: =GETPIVOTDATA("[Measures].[Sum of amount_spent]",$A$22,"[dim_expense_type].[expense_type]","[dim_expense_type].[expense_type].&[Travel and Accommodation Expenses]")/GETPIVOTDATA("[Measures].[Sum of budget_amount]",$A$22,"[dim_expense_type].[expense_type]","[dim_expense_type].[expense_type].&[Travel and Accommodation Expenses]") -> 0.5312816
A41: Utilities (Electricity, Water, Gas) | B41: 3.4076006e+09 | C41: 1.0416783e+09 | D41: =GETPIVOTDATA("[Measures].[Sum of amount_spent]",$A$22,"[dim_expense_type].[expense_type]","[dim_expense_type].[expense_type].&[Utilities (Electricity, Water, Gas)]")/GETPIVOTDATA("[Measures].[Sum of budget_amount]",$A$22,"[dim_expense_type].[expense_type]","[dim_expense_type].[expense_type].&[Utilities (Electricity, Water, Gas)]") -> 0.3056926
A42: Vehicle Fleet Acquisition | B42: 4.8805297e+09 | C42: 1.1712364e+09 | D42: =GETPIVOTDATA("[Measures].[Sum of amount_spent]",$A$22,"[dim_expense_type].[expense_type]","[dim_expense_type].[expense_type].&[Vehicle Fleet Acquisition]")/GETPIVOTDATA("[Measures].[Sum of budget_amount]",$A$22,"[dim_expense_type].[expense_type]","[dim_expense_type].[expense_type].&[Vehicle Fleet Acquisition]") -> 0.23998141
A43: Grand Total | B43: 6.5872976e+10 | C43: 1.6715104e+10 | D43: =GETPIVOTDATA("[Measures].[Sum of amount_spent]",$A$22)/GETPIVOTDATA("[Measures].[Sum of budget_amount]",$A$22) -> 0.25374752

Sheet dim_ministry
A1: ministry_id | B1: ministry_name | C1: minister_name | D1: fiscal_year
A2: MIN1001 | B2: Ministry of Tourism | C2: William Jackson | D2: FY2025
A3: MIN1002 | B3: Ministry of National Defence | C3: Liam Thompson | D3: FY2025
A4: MIN1003 | B4: Ministry of Justice | C4: James Martinez | D4: FY2025
A5: MIN1004 | B5: Ministry of Public Safety | C5: Emma Clark | D5: FY2025
A6: MIN1005 | B6: Ministry of Transport | C6: Charlotte Robinson | D6: FY2025
A7: MIN1006 | B7: Ministry of Fisheries | C7: Olivia Johnson | D7: FY2025
A8: MIN1007 | B8: Ministry of Immigration | C8: Mia Lewis | D8: FY2025
A9: MIN1008 | B9: Ministry of Indigenous Services | C9: Benjamin Jackson | D9: FY2025
A10: MIN1009 | B10: Ministry of Energy and Natural Resources | C10: Noah Taylor | D10: FY2025
A11: MIN1010 | B11: Ministry of Public Works | C11: Daniel Garcia | D11: FY2025
A12: MIN1011 | B12: Ministry of Agriculture | C12: Henry Johnson | D12: FY2025
... A17: MIN1016 | B17: Ministry of Artificial Intelligence | C17: Lucas Johnson | D17: FY2025

Sheet dim_expense_category
A1: expense_category_id | B1: expense_category
A2: CAPEX | B2: Capital
A3: OPEX | B3: Operational

Sheet dim_expense_type
A1: expense_type_id | B1: expense_type | C1: expense_category
A2: CAPEX-01 | B2: Land Acquisition | C2: CAPEX
A3: CAPEX-02 | B3: Major Technology Hardware Purchases | C3: CAPEX
A4: CAPEX-03 | B4: Public Facility Expansion Projects | C4: CAPEX
A5: CAPEX-04 | B5: IT Systems Implementation (ERP, Cybersecurity Systems) | C5: CAPEX
A6: CAPEX-05 | B6: Data Center Development | C6: CAPEX
A7: CAPEX-06 | B7: Vehicle Fleet Acquisition | C7: CAPEX
A8: CAPEX-07 | B8: Building Construction and Renovation | C8: CAPEX
A9: CAPEX-08 | B9: Research and Innovation Capital Projects | C9: CAPEX
A10: CAPEX-09 | B10: Heavy Equipment Purchase | C10: CAPEX
A11: CAPEX-10 | B11: Infrastructure Development Projects | C11: CAPEX
A12: OPEX-01 | B12: Travel and Accommodation Expenses | C12: OPEX
... A21: OPEX-10 | B21: Professional and Consulting Fees | C21: OPEX

Sheet dim_funding_source
A1: funding_source_id | B1: funding_source
A2: FUND-001 | B2: federal_funding
A3: FUND-002 | B3: provincial_funding
A4: FUND-003 | B4: grant_funding
A5: FUND-004 | B5: internally_gen_funding

Sheet fact_approved_budget
A1: budget_id | B1: fiscal_year | C1: ministry_id | D1: expense_category_id | E1: expense_type_id | F1: budget_amount | G1: approval_date
A2: BFY2025-01 | B2: FY2025 | C2: MIN1001 | D2: CAPEX | E2: CAPEX-01 | F2: 1.3546605e+08 | G2: 45633
A3: BFY2025-01 | B3: FY2025 | C3: MIN1001 | D3: CAPEX | E3: CAPEX-02 | F3: 3.7358119e+08 | G3: 45633
A4: BFY2025-01 | B4: FY2025 | C4: MIN1001 | D4: CAPEX | E4: CAPEX-03 | F4: 2.0522056e+08 | G4: 45633
A5: BFY2025-01 | B5: FY2025 | C5: MIN1001 | D5: CAPEX | E5: CAPEX-04 | F5: 2.9652235e+08 | G5: 45633
A6: BFY2025-01 | B6: FY2025 | C6: MIN1001 | D6: CAPEX | E6: CAPEX-05 | F6: 2.0916985e+08 | G6: 45633
A7: BFY2025-01 | B7: FY2025 | C7: MIN1001 | D7: OPEX | E7: OPEX-01 | F7: 41769204 | G7: 45633
A8: BFY2025-01 | B8: FY2025 | C8: MIN1001 | D8: OPEX | E8: OPEX-02 | F8: 19337640 | G8: 45633
A9: BFY2025-01 | B9: FY2025 | C9: MIN1001 | D9: OPEX | E9: OPEX-03 | F9: 28554119 | G9: 45633
A10: BFY2025-01 | B10: FY2025 | C10: MIN1001 | D10: OPEX | E10: OPEX-04 | F10: 17826460 | G10: 45633
A11: BFY2025-01 | B11: FY2025 | C11: MIN1001 | D11: OPEX | E11: OPEX-05 | F11: 63482915 | G11: 45633
A12: BFY2025-01 | B12: FY2025 | C12: MIN1001 | D12: OPEX | E12: OPEX-06 | F12: 12023662 | G12: 45633
A13: BFY2025-02 | B13: FY2025 | C13: MIN1002 | D13: CAPEX | E13: CAPEX-02 | F13: 7.4829135e+09 | G13: 45633
... A196: BFY2025-16 | B196: FY2025 | C196: MIN1016 | D196: OPEX | E196: OPEX-03 | F196: 2.4921511e+08 | G196: 45633

Sheet fact_budget_funding
A1: budget_id | B1: fiscal_year | C1: ministry_id | D1: funding_source_id | E1: funding_amount
A2: BFY2025-01 | B2: FY2025 | C2: MIN1001 | D2: FUND-001 | E2: 7.716247e+08
A3: BFY2025-01 | B3: FY2025 | C3: MIN1001 | D3: FUND-002 | E3: 350738500
A4: BFY2025-01 | B4: FY2025 | C4: MIN1001 | D4: FUND-003 | E4: 210443100
A5: BFY2025-01 | B5: FY2025 | C5: MIN1001 | D5: FUND-004 | E5: 70147700
A6: BFY2025-02 | B6: FY2025 | C6: MIN1002 | D6: FUND-001 | E6: 11451412500
A7: BFY2025-02 | B7: FY2025 | C7: MIN1002 | D7: FUND-002 | E7: 5205187500
A8: BFY2025-02 | B8: FY2025 | C8: MIN1002 | D8: FUND-003 | E8: 3123112500
A9: BFY2025-02 | B9: FY2025 | C9: MIN1002 | D9: FUND-004 | E9: 1041037500
A10: BFY2025-03 | B10: FY2025 | C10: MIN1003 | D10: FUND-001 | E10: 1.7200337e+09
A11: BFY2025-03 | B11: FY2025 | C11: MIN1003 | D11: FUND-002 | E11: 781833500
A12: BFY2025-03 | B12: FY2025 | C12: MIN1003 | D12: FUND-003 | E12: 469100100
A13: BFY2025-03 | B13: FY2025 | C13: MIN1003 | D13: FUND-004 | E13: 156366700
... A65: BFY2025-16 | B65: FY2025 | C65: MIN1016 | D65: FUND-004 | E65: 120492000

Sheet fact_actual_expenditure
A1: transaction_id | B1: transaction_date | C1: trans_date (yyyy-mm) | D1: ministry_id | E1: expense_category_id | F1: expense_type_id | G1: amount_spent
A2: TXN2025-00001 | B2: 45906 | C2: =TEXT(Table3[[#This Row],[transaction_date]], "yyyy-mm") -> 2025-09 | D2: MIN1011 | E2: CAPEX | F2: CAPEX-10 | G2: 2985572.9
A3: TXN2025-00002 | B3: 45965 | C3: =TEXT(Table3[[#This Row],[transaction_date]], "yyyy-mm") -> 2025-11 | D3: MIN1014 | E3: CAPEX | F3: CAPEX-05 | G3: 12635066
A4: TXN2025-00003 | B4: 45718 | C4: =TEXT(Table3[[#This Row],[transaction_date]], "yyyy-mm") -> 2025-03 | D4: MIN1016 | E4: OPEX | F4: OPEX-01 | G4: 2241162.8
A5: TXN2025-00004 | B5: 45684 | C5: =TEXT(Table3[[#This Row],[transaction_date]], "yyyy-mm") -> 2025-01 | D5: MIN1006 | E5: CAPEX | F5: CAPEX-07 | G5: 941863.83
A6: TXN2025-00005 | B6: 45932 | C6: =TEXT(Table3[[#This Row],[transaction_date]], "yyyy-mm") -> 2025-10 | D6: MIN1015 | E6: OPEX | F6: OPEX-02 | G6: 4462901.4
A7: TXN2025-00006 | B7: 45976 | C7: =TEXT(Table3[[#This Row],[transaction_date]], "yyyy-mm") -> 2025-11 | D7: MIN1016 | E7: CAPEX | F7: CAPEX-05 | G7: 21126094
A8: TXN2025-00007 | B8: 45813 | C8: =TEXT(Table3[[#This Row],[transaction_date]], "yyyy-mm") -> 2025-06 | D8: MIN1003 | E8: CAPEX | F8: CAPEX-05 | G8: 908018.27
A9: TXN2025-00008 | B9: 45977 | C9: =TEXT(Table3[[#This Row],[transaction_date]], "yyyy-mm") -> 2025-11 | D9: MIN1004 | E9: OPEX | F9: OPEX-07 | G9: 6874274.4
A10: TXN2025-00009 | B10: 45847 | C10: =TEXT(Table3[[#This Row],[transaction_date]], "yyyy-mm") -> 2025-07 | D10: MIN1010 | E10: OPEX | F10: OPEX-03 | G10: 2015492.4
A11: TXN2025-00010 | B11: 45779 | C11: =TEXT(Table3[[#This Row],[transaction_date]], "yyyy-mm") -> 2025-05 | D11: MIN1010 | E11: CAPEX | F11: CAPEX-01 | G11: 12648713
A12: TXN2025-00011 | B12: 45889 | C12: =TEXT(Table3[[#This Row],[transaction_date]], "yyyy-mm") -> 2025-08 | D12: MIN1013 | E12: OPEX | F12: OPEX-04 | G12: 138171.07
A13: TXN2025-00012 | B13: 45720 | C13: =TEXT(Table3[[#This Row],[transaction_date]], "yyyy-mm") -> 2025-03 | D13: MIN1011 | E13: CAPEX | F13: CAPEX-02 | G13: 1534934.3
... A3501: TXN2025-03500 | B3501: 45806 | C3501: =TEXT(Table3[[#This Row],[transaction_date]], "yyyy-mm") -> 2025-05 | D3501: MIN1003 | E3501: OPEX | F3501: OPEX-01 | G3501: 19262780
